[
    {
        "name": "Roofs",
        "description": "Keep your head dry when it rains.",
        "image": "test.png",
        "type": "category",
        "parent": "Structures"
    },
    {
        "id": 205,
        "name": "Thatch roof",
        "description": "A thatched roof to protect you from the elements. Not stable enough to build on.",
        "image": "thatch roof.png",
        "minLevel": 3,
        "engrams": 3,
        "prerequisites": [],
        "type": "item",
        "parent": "Roofs"
    },
    {
        "id": 206,
        "name": "Sloped thatch roof",
        "description": "An inclined Thatch roof. Slightly different angle than the ramp.",
        "image": "sloped thatch roof.png",
        "minLevel": 5,
        "engrams": 3,
        "prerequisites": ["Thatch roof"],
        "type": "item",
        "parent": "Roofs"
    },
    {
        "id": 207,
        "name": "Sloped wooden roof",
        "description": "An inclined wooden roof. Slightly different angle than the ramp.",
        "image": "sloped wooden roof.png",
        "minLevel": 10,
        "engrams": 4,
        "prerequisites": ["Sloped thatch roof", "Wooden ceiling"],
        "type": "item",
        "parent": "Roofs"
    },
    {
        "id": 208,
        "name": "Sloped stone roof",
        "description": "An inclined stone roof. Slightly different angle than the ramp.",
        "image": "sloped stone roof.png",
        "minLevel": 20,
        "engrams": 4,
        "prerequisites": ["Sloped wooden roof", "Stone ceiling"],
        "type": "item",
        "parent": "Roofs"
    },
    {
        "id": 209,
        "name": "Sloped metal roof",
        "description": "An inclined metal roof. Slightly different angle than the ramp.",
        "image": "sloped metal roof.png",
        "minLevel": 35,
        "engrams": 10,
        "prerequisites": ["Sloped stone roof", "Metal ceiling"],
        "type": "item",
        "parent": "Roofs"
    }
]
